{
  "0": [],
  "600": [
    {
      "to": 0,
      "ping": 100
    },
    {
      "to": 1,
      "ping": 100
    },
    {
      "to": 2,
      "ping": 100
    },
    {
      "to": 3,
      "ping": 100
    },
    {
      "to": 4,
      "ping": 100
    },
    {
      "to": 5,
      "ping": 100
    },
    {
      "to": 6,
      "ping": 100
    },
    {
      "to": 7,
      "ping": 100
    },
    {
      "to": 8,
      "ping": 100
    },
    {
      "to": 9,
      "ping": 100
    },
    {
      "to": 10,
      "ping": 100
    },
    {
      "to": 11,
      "ping": 100
    },
    {
      "to": 12,
      "ping": 100
    },
    {
      "to": 13,
      "ping": 100
    },
    {
      "to": 14,
      "ping": 100
    },
    {
      "to": 15,
      "ping": 100
    },
    {
      "to": 16,
      "ping": 100
    },
    {
      "to": 17,
      "ping": 100
    },
    {
      "to": 18,
      "ping": 100
    },
    {
      "to": 19,
      "ping": 100
    },
    {
      "to": 20,
      "ping": 100
    },
    {
      "to": 21,
      "ping": 100
    },
    {
      "to": 22,
      "ping": 100
    },
    {
      "to": 23,
      "ping": 100
    },
    {
      "to": 24,
      "ping": 100
    },
    {
      "to": 25,
      "ping": 100
    },
    {
      "to": 26,
      "ping": 100
    },
    {
      "to": 27,
      "ping": 100
    },
    {
      "to": 28,
      "ping": 100
    },
    {
      "to": 29,
      "ping": 100
    },
    {
      "to": 30,
      "ping": 100
    },
    {
      "to": 31,
      "ping": 100
    },
    {
      "to": 32,
      "ping": 100
    },
    {
      "to": 33,
      "ping": 100
    },
    {
      "to": 34,
      "ping": 100
    },
    {
      "to": 35,
      "ping": 100
    },
    {
      "to": 36,
      "ping": 100
    },
    {
      "to": 37,
      "ping": 100
    },
    {
      "to": 38,
      "ping": 100
    },
    {
      "to": 39,
      "ping": 100
    },
    {
      "to": 40,
      "ping": 100
    },
    {
      "to": 41,
      "ping": 100
    },
    {
      "to": 42,
      "ping": 100
    },
    {
      "to": 43,
      "ping": 100
    },
    {
      "to": 44,
      "ping": 100
    },
    {
      "to": 45,
      "ping": 100
    },
    {
      "to": 46,
      "ping": 100
    },
    {
      "to": 47,
      "ping": 100
    },
    {
      "to": 48,
      "ping": 100
    },
    {
      "to": 49,
      "ping": 100
    },
    {
      "to": 50,
      "ping": 100
    },
    {
      "to": 51,
      "ping": 100
    },
    {
      "to": 52,
      "ping": 100
    },
    {
      "to": 53,
      "ping": 100
    },
    {
      "to": 54,
      "ping": 100
    },
    {
      "to": 55,
      "ping": 100
    },
    {
      "to": 56,
      "ping": 100
    },
    {
      "to": 57,
      "ping": 100
    },
    {
      "to": 58,
      "ping": 100
    },
    {
      "to": 59,
      "ping": 100
    },
    {
      "to": 60,
      "ping": 100
    },
    {
      "to": 61,
      "ping": 100
    },
    {
      "to": 62,
      "ping": 100
    },
    {
      "to": 63,
      "ping": 100
    },
    {
      "to": 64,
      "ping": 100
    },
    {
      "to": 65,
      "ping": 100
    },
    {
      "to": 66,
      "ping": 100
    },
    {
      "to": 67,
      "ping": 100
    },
    {
      "to": 68,
      "ping": 100
    },
    {
      "to": 69,
      "ping": 100
    },
    {
      "to": 70,
      "ping": 100
    },
    {
      "to": 71,
      "ping": 100
    },
    {
      "to": 72,
      "ping": 100
    },
    {
      "to": 73,
      "ping": 100
    },
    {
      "to": 74,
      "ping": 100
    },
    {
      "to": 75,
      "ping": 100
    },
    {
      "to": 76,
      "ping": 100
    },
    {
      "to": 77,
      "ping": 100
    },
    {
      "to": 78,
      "ping": 100
    },
    {
      "to": 79,
      "ping": 100
    },
    {
      "to": 80,
      "ping": 100
    },
    {
      "to": 81,
      "ping": 100
    },
    {
      "to": 82,
      "ping": 100
    },
    {
      "to": 83,
      "ping": 100
    },
    {
      "to": 84,
      "ping": 100
    },
    {
      "to": 85,
      "ping": 100
    },
    {
      "to": 86,
      "ping": 100
    },
    {
      "to": 87,
      "ping": 100
    },
    {
      "to": 88,
      "ping": 100
    },
    {
      "to": 89,
      "ping": 100
    },
    {
      "to": 90,
      "ping": 100
    },
    {
      "to": 91,
      "ping": 100
    },
    {
      "to": 92,
      "ping": 100
    },
    {
      "to": 93,
      "ping": 100
    },
    {
      "to": 94,
      "ping": 100
    },
    {
      "to": 95,
      "ping": 100
    },
    {
      "to": 96,
      "ping": 100
    },
    {
      "to": 97,
      "ping": 100
    },
    {
      "to": 98,
      "ping": 100
    },
    {
      "to": 99,
      "ping": 100
    }
  ]
}